myln/__init__.py
myln/abbreviations.py
myln/compressor.py
myln-0.1.2.dist-info/LICENSE
myln-0.1.2.dist-info/METADATA
myln-0.1.2.dist-info/WHEEL
myln-0.1.2.dist-info/top_level.txt
myln-0.1.2.dist-info/RECORD
